<?xml version="1.0" encoding="UTF-8" standalone="no"?>
<!-- saved from url=(0014)about:internet -->
<pk><wd nm="rea" rd="5,0:36|9,0:478|27,0:1101,1118|28,0:1104|31,0:1051|51,0:405,444,494,948,1061,1404|53,128:10,25,46,83,129,171,248,393,580,719,970"/><wd nm="rea," rd="53,64:836"/><wd nm="read" rd="48,0:5320"/><wd nm="reada" rd="55,0:5799"/><wd nm="reader" rd="16,0:2946"/><wd nm="reado" rd="16,0:267|28,0:688|31,0:632|43,0:90|48,0:6419|51,0:682|54,0:413,1131|55,0:4501"/><wd nm="reados" rd="17,0:932"/><wd nm="realices" rd="55,0:1326"/><wd nm="realizado" rd="51,0:901"/><wd nm="realizar" rd="11,0:1665|27,0:1703|46,0:182|47,32:924,1215,1237,2021|48,0:277,498,2174|51,0:819,845"/><wd nm="realizará" rd="48,0:2809"/><wd nm="realizas" rd="46,0:48"/><wd nm="really" rd="37,0:158"/><wd nm="reamos" rd="12,0:148"/><wd nm="rean" rd="47,0:1576|48,0:3470"/><wd nm="rear" rd="1,0:496|3,0:156,223|5,128:0,16,62,133,269,369,1085,1763,2489|6,128:0,22,245,1433|7,1:19,1054|9,0:280,529|10,0:175,697|11,32:69,446,825,887,1213|12,64:213,269,304,504,1012,1203,1310,1621|14,0:221,735|25,32:270,455|26,0:1574,3203|27,0:676,720,758,844,929,957,1030,1055,1266,1575|33,0:299,411|46,128:0,22,301,568,1209,1669|47,64:2252,2482|49,32:406,504,575,745|51,0:63,182,304,436|52,128:0,19,42,264,445|54,32:66,457,542|55,0:104,4339,4545,5092,5614|59,32:18,128,401"/><wd nm="rearlo" rd="11,0:1469"/><wd nm="rearon" rd="42,0:527"/><wd nm="reará" rd="37,0:479"/><wd nm="reas" rd="7,0:833|27,2:1024,1049,1060,1768|37,0:189|47,0:564|48,0:6465|51,128:11,32,48,104,139,169,214,259,324,346,700,715,792,977,1302,1376,1478,1506,1572,1597,1702,1730,1777,1886,2055,2287|52,128:13,32,57,82,104,147,175,209,276,308,458|53,0:64,288,324,481,607"/><wd nm="reas," rd="51,64:2161"/><wd nm="reas ical" rd="51,0:367"/><wd nm="rebota" rd="22,0:83"/><wd nm="recciones" rd="7,0:1311,1339,1459|11,64:304,339,394,751,923,1013,1093,1164,1340,1406,1488,1581,1696,1726,1876,2199|12,128:13,37,59,363,713,880,1034,1067,1164,1246,1324,1488,1739|13,0:162,204,251,367|14,128:20,61,190,369,409,486,540,707,749,880|15,0:188,302|18,0:159,268|22,0:933,975|23,128:20,47,185,318,555,2012,2457,2639,2766,3012|26,0:1894|27,2:833,875|42,0:1762|45,0:1247|47,32:714,759,1115|55,4:159,4752,4857,4895,4963,5039"/><wd nm="recciones," rd="11,64:2443|12,64:1609"/><wd nm="rección" rd="5,0:1312|10,0:255,587|11,0:524,1546|12,0:395,603|14,0:258,606|18,0:308|20,0:660,742,796,900,1082,1108,1154|22,0:148,222,578,622,894|23,0:464,522,921,2186,2301,2369|26,0:1791,1816,3040,3934,3967|27,0:1429|31,0:279|37,0:249,422|48,0:3822,3893|54,0:488|55,0:2727,2852,4576|56,0:859,1046,1143|57,0:118,463|58,128:13,44,131,402,679,929"/><wd nm="rece" rd="7,0:314|34,0:390|45,0:1346|48,0:4197|56,0:234"/><wd nm="recen" rd="35,0:788"/><wd nm="recer" rd="26,0:1539"/><wd nm="recerá" rd="7,0:1772|23,0:351,1578,2347|46,0:471"/><wd nm="recerán" rd="23,0:1424"/><wd nm="recha" rd="11,0:1625|18,0:844|26,0:1086|51,0:1161,1360|55,0:2221"/><wd nm="rechaza" rd="22,0:66,271,346,552"/><wd nm="rechazado" rd="22,0:488"/><wd nm="rechazados" rd="22,0:1029"/><wd nm="rechazan" rd="22,0:783,826"/><wd nm="rechazar" rd="3,0:301"/><wd nm="recho" rd="37,0:586|53,0:373"/><wd nm="rechos" rd="1,0:674|8,0:659|16,0:3059|19,0:903|20,0:1607|21,0:1005|22,0:1104|23,0:2505|24,0:485|26,0:4036|33,0:870|35,0:1570|42,0:1957|43,0:1146|44,0:571|45,0:1579|48,0:6643|51,0:1929|57,0:586|59,0:818|60,0:60"/><wd nm="reciban" rd="25,0:385"/><wd nm="recibas" rd="25,0:310"/><wd nm="recibes" rd="3,0:327|35,0:1016|38,0:74|55,0:900|57,0:224,274"/><wd nm="recibido" rd="10,0:55|14,0:87|20,0:832|38,128:15,52,647|48,0:5201|55,0:2890|57,0:144"/><wd nm="recibidos" rd="33,0:787"/><wd nm="recibir" rd="9,0:494|22,0:1006|24,0:265|42,0:553|57,0:98,414|58,0:332,362|59,0:469"/><wd nm="recibirá" rd="20,0:931"/><wd nm="recibirás" rd="16,0:1707"/><wd nm="recibiste" rd="30,0:622"/><wd nm="recibió" rd="20,0:863"/><wd nm="recida" rd="31,0:99|47,0:1593|48,0:3487"/><wd nm="recido" rd="48,0:6100,6174"/><wd nm="reciente" rd="16,0:1328|30,0:405|43,0:420"/><wd nm="recientes" rd="34,0:470|55,0:741|56,0:329"/><wd nm="recipients" rd="18,0:365"/><wd nm="recomendamos" rd="42,0:1796|46,0:86"/><wd nm="recomienda" rd="55,0:509"/><wd nm="reconocer" rd="16,0:1275"/><wd nm="recordar" rd="56,0:1262,1354"/><wd nm="recordarme" rd="56,64:2125"/><wd nm="recta" rd="16,0:1225|22,0:231,587"/><wd nm="rectamente" rd="16,0:715,1160|37,0:124|55,0:945"/><wd nm="rectivas" rd="25,0:345"/><wd nm="recto" rd="16,0:1300|27,0:1628|29,128:14,35,59,244,365,486|55,0:6346"/><wd nm="rectos" rd="29,0:195|55,4:6179,6197,6290"/><wd nm="recuencia" rd="6,0:419,826|46,0:74"/><wd nm="recuentemente" rd="16,2:1815"/><wd nm="recuperar" rd="21,32:736|32,0:165|33,0:201|41,0:446|44,64:0,30,344,422,463,807"/><wd nm="recurrente" rd="6,128:12,487,1445|7,0:492"/><wd nm="recurrentes" rd="6,1:36,59,132,232,343|7,0:556"/><wd nm="recursos" rd="7,0:1203"/><wd nm="redacción" rd="18,0:130,560|19,0:251,622|24,0:439|35,0:605|45,0:298,685,1232,1471|55,0:173"/><wd nm="redacta" rd="17,0:200"/><wd nm="redactado" rd="20,0:288|35,0:487"/><wd nm="redactados" rd="26,0:865"/><wd nm="redactando" rd="21,0:64,242"/><wd nm="redactar" rd="17,0:235|18,1:0,22,48,79|21,0:455,869|24,0:50,298|27,0:407|28,0:279|55,4:3375,3385,3411,3473"/><wd nm="redactas" rd="21,0:337,546,568"/><wd nm="redactes" rd="45,0:1501"/><wd nm="redeterminada" rd="3,0:582|8,0:194|24,0:339,372|34,128:16,72,191,240,694,951,1081|40,0:291|51,0:153|54,0:1023|55,0:1770,2389,2468,5785|56,0:623,708,1836"/><wd nm="redeterminadas" rd="55,0:65"/><wd nm="redeterminado" rd="48,0:5422|55,0:460"/><wd nm="redeterminados" rd="5,0:1203"/><wd nm="reduciendo" rd="23,0:299"/><wd nm="reducirá" rd="23,0:777"/><wd nm="reemplazará" rd="23,0:1761"/><wd nm="reenviado" rd="19,0:430,653|48,0:5231,5242"/><wd nm="reenviados" rd="55,0:4190"/><wd nm="reenviar" rd="19,64:0,17,52,93,508,548,563,826,1021|26,0:3012,3923|27,0:636|55,0:2740,3980,5710|58,64:152,251,378,432,797"/><wd nm="reenviarlo" rd="58,0:237"/><wd nm="reenviarlos" rd="25,0:230"/><wd nm="reenvía" rd="22,0:532|26,0:3021"/><wd nm="reenvían" rd="19,0:282|26,0:3945"/><wd nm="reenvías" rd="55,0:4041"/><wd nm="reenvío" rd="58,128:24,55,690,940"/><wd nm="rees" rd="31,0:544|35,0:264|46,0:101"/><wd nm="referencia" rd="16,2:1762|55,0:230,282,335"/><wd nm="referencias" rd="3,0:689|7,0:597|8,0:138,433|12,0:681|19,0:237|21,32:204,392,463|23,0:2436|24,0:425|25,0:508|27,2:1331|29,0:176|30,0:173|33,0:264|34,0:298,769|40,0:252|45,0:744,1410|54,0:562|55,128:13,38,53,255,6561,6686|56,0:753|57,0:376|58,0:283|59,0:429"/><wd nm="refieres" rd="34,0:590,672|56,0:449"/><wd nm="refijo" rd="45,0:991,1057|47,0:952,1642|48,0:921|55,0:3789,3803,4094,4134,4149"/><wd nm="refleja" rd="7,0:615"/><wd nm="reflejada" rd="7,0:1883"/><wd nm="reflejará" rd="7,0:758"/><wd nm="rega" rd="51,0:1563"/><wd nm="regar" rd="22,128:21,50,114,1243,1372"/><wd nm="regarlo" rd="26,0:2928"/><wd nm="regir" rd="22,0:513"/><wd nm="regla" rd="25,0:286"/><wd nm="reglas" rd="25,64:63,1905|26,0:85|33,0:304|48,0:2226|55,0:6004,6109"/><wd nm="regúntame" rd="20,0:631"/><wd nm="reinicies" rd="56,0:1445"/><wd nm="relacionado" rd="47,0:1954"/><wd nm="relacionados" rd="3,0:859,876|26,0:1949|30,0:1484|42,0:1891,1908"/><wd nm="relevante" rd="16,0:158|35,0:1273|42,0:792"/><wd nm="rellenando" rd="23,0:1176"/><wd nm="rellenar" rd="12,0:532"/><wd nm="remitente" rd="20,0:189,645,1073,1561|26,0:1020|30,0:529|33,0:359|42,0:262|45,0:59,96,171|48,0:3810"/><wd nm="remitentes" rd="42,0:1867"/><wd nm="remota" rd="5,64:1346,1880,2127|51,0:378"/><wd nm="remoto" rd="48,0:5267"/><wd nm="ren" rd="20,0:1451|48,0:1962|56,0:1943"/><wd nm="rencia" rd="16,2:1762|55,0:230,282,335"/><wd nm="rencias" rd="3,0:689|7,0:597|8,0:138,433|12,0:681|19,0:237|21,32:204,392,463|23,0:2436|24,0:425|25,0:508|27,2:1331|29,0:176|30,0:173|33,0:264|34,0:298,769|40,0:252|45,0:744,1410|54,0:562|55,128:13,38,53,255,6561,6686|56,0:753|57,0:376|58,0:283|59,0:429"/><wd nm="render" rd="47,0:103"/><wd nm="reno" rd="23,0:696|48,0:3194,3226,3283,3334,3884"/><wd nm="rente" rd="6,128:12,487,1445|7,0:492|20,0:805|55,0:974"/><wd nm="rentes" rd="1,0:277|3,0:161|5,0:91|6,1:36,59,132,232,343|7,0:556,713|23,0:1623|48,0:2778"/><wd nm="reo" rd="1,0:105|4,0:247|5,0:633|7,0:1472,1671,1729|10,0:81,266,598|11,0:317,535,900,936,1296,1501,1594|12,0:376,802|14,0:113,269,617|18,0:172|20,64:58,259,449,671,911,1119,1552,1734|22,0:250,312,729|23,64:932,2779|24,0:249|25,0:85,403,542|26,0:939,3051,3978|27,2:176,384,390,432,714,1440,1589|28,128:26,51,75,266,721,1250|30,0:196,226,341|31,128:19,44,77,290,753,1011,1096,1298|33,128:23,52,123,287,581,1011|34,0:641|35,1:38,669,993,1050,1114,1142,1174,1213|37,0:146|38,0:274|40,128:21,48,438|41,0:338|42,0:55,994,1408,1607|43,128:6,18,109,1264,1480|45,64:1707|47,0:518|48,0:3833|50,128:17,40,583|54,0:106,438|55,4:140,826,1492,2383,3249,4379,4526,5971,6026,6129|56,0:500,1057,1666,1961|57,1:45,88,129,397,474|58,0:142,315|59,0:452,634"/><wd nm="repeticiones" rd="6,0:747,890,1074"/><wd nm="repetición" rd="6,0:431,702"/><wd nm="repetidos" rd="6,0:1276"/><wd nm="repetir" rd="6,0:271,371|7,0:534|25,0:718"/><wd nm="repite" rd="6,0:805,949,1134"/><wd nm="repiten" rd="6,0:83,148"/><wd nm="representar" rd="26,0:2528"/><wd nm="representarán" rd="1,0:239"/><wd nm="reproducir" rd="16,0:2740"/><wd nm="reproductor" rd="16,0:2800"/><wd nm="requiere" rd="12,0:249"/><wd nm="res" rd="0,0:249|1,0:232|2,0:126|4,0:117|5,0:724,954,1402,1632|6,0:558|7,0:1143,1247,1363,1524|10,0:529|11,0:244,300,335,628,785,1304,1658,1773|13,0:265,426|14,0:568|15,128:11,43,518|16,0:348,433,1032,1427,1948,1995,2019|18,0:214,394,442,745,1013,1100|19,0:321,541|21,32:138,280,418,512,604,722,768,958|22,0:701|23,0:95,425,730,1238,2067,2136|26,0:303,1206,1975,2546|27,0:1480|30,0:271|31,0:492|32,0:379,509,600,656|34,0:171,456,590,672|35,2:94,447,520,574|36,0:146|39,0:193|40,0:126|42,0:1391,1477|43,0:706|44,0:415|45,0:462,731|46,0:681,806,1202|47,0:501|48,0:538,1248,1522,1597,1709,2043,2736|49,0:1073|51,0:688,1675|52,0:236|53,0:137|54,0:192,886|55,0:727,1547,1645,1792,2240,3603,3998,4465,4791,5226,5303|56,0:315,449,565,1816|58,0:425,453|59,0:563"/><wd nm="resa" rd="5,0:208|11,0:199,571,1741|12,0:420|22,0:990"/><wd nm="resalta" rd="51,0:751"/><wd nm="resaltada" rd="23,0:1221,1820"/><wd nm="resaltadas" rd="1,0:352"/><wd nm="resaltados" rd="30,0:468"/></pk>
