<?xml version="1.0" encoding="UTF-8" standalone="no"?>
<!-- saved from url=(0014)about:internet -->
<pk><wd nm="プリファレンス、[全般]タブ" rd="173,64:1469"/><wd nm="プリファレンス、カレンダー" rd="172,64:1668"/><wd nm="プリファレンス、共有" rd="135,64:2002"/><wd nm="プリファレンス、変更する" rd="154,64:581"/><wd nm="プリファレンス、閲覧ペインを表示" rd="121,64:781"/><wd nm="プリファレンスを変更する" rd="154,128:693"/><wd nm="プリファレンスを指定する" rd="91,128:1106|171,128:822|172,128:1888|173,128:1583|174,128:2386|175,128:2254|176,128:3959"/><wd nm="プリファレンスビュー" rd="5,0:457|16,0:119|31,0:95|32,0:21,105"/><wd nm="プリファレンスフォルダ" rd="135,0:970"/><wd nm="プリンタ" rd="55,0:28,138,161|119,0:80,202,226"/><wd nm="プリンタダイアログ" rd="28,0:222,256"/><wd nm="プリート" rd="40,0:546|43,0:286|66,64:16,25,455,588,1358,1397,1673|171,0:268,520,540,649|176,0:1298,1330"/><wd nm="プリートする" rd="66,64:1557"/><wd nm="プリートリスト" rd="171,0:701"/><wd nm="プルダウンメニュー" rd="44,0:514"/><wd nm="プレゼンテーション" rd="3,0:213"/><wd nm="プレッドシート" rd="3,0:204|59,0:854|118,0:36|131,0:124"/><wd nm="プレッドシートプログラム" rd="57,0:1187"/><wd nm="プレビュー" rd="109,0:634|121,0:57|174,0:883|181,0:218"/><wd nm="プレビューオプション" rd="176,0:597"/><wd nm="プレビューペイン" rd="3,4:2152,2168,2216,2231,2253,2269|102,0:1066,1086|142,4:498,515,556,606,626,661"/><wd nm="プレビューペイン、オンとオフを切り替える" rd="121,64:897"/><wd nm="プレファレンス" rd="79,0:221"/><wd nm="プレフィックス" rd="123,0:494,543,555|175,0:935,1154,1264,1335"/><wd nm="プレースホルダー" rd="83,0:115,290"/><wd nm="プレーヤー" rd="57,0:1666"/><wd nm="プロ" rd="118,0:29"/><wd nm="プログラム" rd="4,0:189|45,0:260,290|56,0:319|57,0:1187,1344,1515,1578|61,0:590,620|93,0:1027|118,0:916|157,0:556,586|181,0:86"/><wd nm="プログラムファイル" rd="57,0:1372"/><wd nm="プロジェクター" rd="7,0:1165"/><wd nm="プロジェクト" rd="54,0:461,480,500,527|142,0:119,129|143,0:754"/><wd nm="プロソフト" rd="133,0:685"/><wd nm="プロツール" rd="77,0:198"/><wd nm="プロバイダ" rd="151,0:426,636|166,0:308,341,550"/><wd nm="プロパティ" rd="1,0:628,1377|9,0:286|18,0:949,1818|51,0:745,1472|72,0:114|73,0:791|75,0:80,184,221,297,336,443|77,0:632|135,0:917,1081,1102|136,0:1162,1259|149,0:711,1226,1409"/><wd nm="プロード" rd="2,0:217,313|3,4:62,236,472,965,978,1091,1117,1149,1180,1202,1221,1322,1339,1365,1434,1488,1522,1562,1633,1692,1788,1829,1940|4,0:531,541,566|41,0:319,329|77,0:769,826,864|84,0:1087,1140|182,0:267,339"/><wd nm="プロードする" rd="182,64:780"/><wd nm="プロードファイル" rd="3,0:1884"/><wd nm="プ連絡先" rd="42,64:909,1024"/><wd nm="プ連絡先リストを作成する" rd="42,128:1238"/><wd nm="ヘッダー" rd="3,0:2044|10,0:348|11,0:121|12,0:225|26,0:254|30,0:218|41,0:71,873,981|48,32:205,260|56,0:613,1200,1231|58,0:562|59,0:399|60,0:167,187|61,4:58,62,96,147|64,0:259|78,0:108,143,178,221,255,267,349,393,441,476,589|81,0:646|85,0:302,573|92,0:88|102,0:683,954|109,0:126|110,0:126|111,0:369,466|118,0:301|123,0:729|126,0:246,348|128,0:2095,2206,2255,2311|132,0:287|175,0:1042,1080,1149,1205,1243"/><wd nm="ヘッダー、含める" rd="175,64:1571"/><wd nm="ヘッダーを変更する" rd="102,64:1373"/><wd nm="ヘッダー情報を含める" rd="175,64:1798"/><wd nm="ヘッダー情報を表示する" rd="175,64:1911,2135"/><wd nm="ヘルスケアプログラム" rd="61,0:590"/><wd nm="ヘルプ" rd="94,0:338|109,0:165"/><wd nm="ヘルプトピック" rd="154,0:310"/><wd nm="ベット" rd="78,0:50"/><wd nm="ベル" rd="32,0:444|39,0:87|41,0:430,473,500|61,0:269|73,0:649|77,0:445|97,0:393|99,0:276"/><wd nm="ベロープ" rd="53,0:984,996"/><wd nm="ベント" rd="5,64:6,46,245,250,271,969|6,0:61,159|7,0:40,696,799|9,0:223|27,64:559,680|31,64:2,13,41,55,61,1838,1942|32,0:567|80,0:211,236|84,0:822|172,0:404"/><wd nm="ベントについて" rd="5,128:1384"/><wd nm="ベントを予定する" rd="31,128:2156"/><wd nm="ベース" rd="100,0:182,311|162,0:125,255"/><wd nm="ベータ" rd="89,1:29"/><wd nm="ベート" rd="6,0:137|7,0:652,680|16,0:1614|18,4:690,732,787,807,861,1130,1163,1464,1497|22,0:107|27,1:3,20,37,131,261,304,323,361,403,443|30,0:723,743,772,819|31,0:1622|32,0:513|135,0:1283,1316,1617,1650|172,0:234,311,341,370,388"/><wd nm="ベートのマークを付ける" rd="7,64:1480|27,128:795,912"/><wd nm="ベートカレンダーイベント" rd="27,64:559,680"/><wd nm="ベート予約" rd="7,64:1372"/><wd nm="ベート予約、詳細を共有する" rd="18,64:2537"/><wd nm="ペイン" rd="1,0:1522|3,4:937,2152,2168,2216,2231,2253,2269|11,0:164|13,0:319|15,0:188|30,0:170|34,0:364|41,0:861|46,0:210|53,2:79,94,198,774,1300|54,0:88|70,0:173|71,0:295,337|74,0:115|76,0:156|82,0:474|85,0:398,405,428|86,0:67|87,0:290|88,0:546|90,0:251|92,0:328|95,0:311|97,0:180,423|100,0:413|101,0:260|102,0:114,498,515,578,613,641,713,926,984,1066,1086|103,0:89,112|105,64:8,840,1075,1182|106,0:893,1111|108,0:73|109,0:344,502,531,612,618,657,689,712|110,0:40|111,0:754|117,0:70,117,147|120,0:314,410,440,488,522,555,566,610|121,64:2,14,30,69,132,165,172,213,219,249,268,284,310,327,333,392,439,452,488,541,653,1017|124,0:317,339,392|125,0:123,146,175,190,332,341,452,469,484|126,0:53,66,108,329|128,0:1202,1343,1352,1478,1486,1501|130,0:196,306|131,0:19,62,195,377,477,595,807,823,869,983,1013|132,0:362,519,540|133,0:453|136,0:345,387,1383|138,0:187,194,242,715|139,0:26|141,0:418,544|142,4:237,372,406,498,515,556,568,606,626,661,799,1124|143,0:135,341,360,533,847|144,0:49|145,0:128,307|146,0:62|147,0:152|148,0:135,258,342|154,0:261|168,0:115|172,0:435|173,0:868|174,0:1176,1201,1252,1283,1383|176,0:134,397,610,2304|181,0:391,465"/><wd nm="ペイン、オンとオフを切り替える" rd="53,64:1894|121,64:897,1122"/><wd nm="ペイン、ビュー" rd="109,64:1631"/><wd nm="ペイン、列ヘッダーを変更する" rd="102,64:1373"/><wd nm="ペインでメールを読む" rd="121,128:1347"/><wd nm="ペインを表示" rd="121,64:781,1239"/><wd nm="ペインウィンドウ" rd="85,0:371"/><wd nm="ペイント" rd="57,0:1488"/><wd nm="ペインビュー" rd="53,64:2011|109,64:669,878|121,2:152"/><wd nm="ペインビューを設定する" rd="176,64:3734"/><wd nm="ペット" rd="53,0:1143|174,0:908"/><wd nm="ペル" rd="58,0:471|69,0:34,196,353,405,471,533"/><wd nm="ペルチェック" rd="58,0:484|69,64:0,12,55,89,130,148,177,297,329,415,432,452,715|76,0:81|175,0:635,675|176,0:960"/><wd nm="ペルチェック、必須として設定する" rd="175,64:1454"/><wd nm="ペルチェックを使用する" rd="69,128:1045"/><wd nm="ペルミス" rd="175,0:689,708"/><wd nm="ページ" rd="0,0:388,595|1,32:1515,1625|3,0:2383|4,0:653,748,766,788|7,0:2,238,502|13,0:69|14,0:119|16,0:1476|18,0:1959|20,0:95|21,0:165|22,0:226|28,0:131,154|30,0:1119|31,0:1484|32,2:90,456|34,0:100|35,0:510|36,0:144,452,629|37,0:180,530|38,0:42|39,0:35|43,0:358|55,0:226|57,0:511|58,0:82|59,0:131,178,237,296,451|66,0:1386|68,0:265|69,0:112|73,0:1037|76,64:3,76,106,221,248,296,394,625|77,2:74,122,248,570,583,730,897,995|79,0:718|81,0:2080|84,0:1052|94,0:608|98,0:279|102,0:470|103,1:3,21|107,0:99|108,0:263|109,0:109|119,0:340|123,0:142,324|129,0:428|133,0:42,399|135,64:280,301,424,2217|136,0:412,433,1267|143,0:48,96,891,1162,1254|144,0:103|146,0:169|147,0:172|156,0:348|158,0:119|164,0:51,122,157|170,0:704,934|173,0:718,760|176,0:146,273,448,860,1181,1401,1589,1789,1955,2023,2140|177,0:63|182,0:334"/><wd nm="ページ、文書" rd="76,64:734"/><wd nm="ページについて" rd="7,128:1913"/><wd nm="ページに追加する" rd="75,64:577"/><wd nm="ページをカスタマイズする" rd="103,128:1096"/><wd nm="ページを作成する" rd="76,128:840,954"/><wd nm="ページ用のリッチテキストエディタ" rd="77,64:1229"/><wd nm="ペース" rd="83,0:359,642|109,128:16,1740|128,0:982"/><wd nm="ホスト" rd="151,0:526"/><wd nm="ホルダー" rd="83,0:115,290"/><wd nm="ホワイトリスト" rd="79,64:1045"/><wd nm="ボタン" rd="25,0:320|41,0:53|49,0:180|52,0:629,671,691|61,0:418|81,0:1746|85,0:79,121,560|92,0:432|93,0:1149|98,0:259,290,469,486|111,0:77|124,0:356|131,0:222|147,0:131|152,0:40|156,0:181|157,0:249|161,0:517,1010|176,0:500"/><wd nm="ボックス" rd="7,0:966,1053,1129|8,0:314|9,0:24|11,0:188|14,0:225,350|15,0:387,452|16,0:1450|18,0:749,844,1180,1514|21,0:255|31,0:1458|32,0:1252,1322,1346|33,0:351|40,0:398|41,0:657|42,0:535,615|44,0:80|48,0:133,624,703|52,0:525|53,0:118|56,0:700,873,1038,1303|58,0:440|65,0:169|66,0:1339|71,0:358,519,631,695|73,0:0,384|74,0:161,292,312,508|79,1:13,776|80,0:973,1006,1041,1114|81,0:1291,2117|84,0:689,1238|85,0:613|87,0:507|89,0:107|91,0:151,169|93,0:813|97,0:107,266|100,0:292|101,0:467|102,0:165,255|103,4:44,177,210,574,663|108,0:134|109,0:422|118,0:626,664|123,0:504|124,32:59,110,137|125,0:315,491,577|126,0:399|128,0:1326,1461,1508,1610|129,0:120,345,573,708,829|131,0:232,280,517,609,1041|133,0:238,328|135,0:1333,1667|136,0:1373|142,0:1060|143,0:1208|144,0:217,295|145,0:232|151,0:611,734,928,950,1081|154,0:78|156,0:72,443,521,652,935,1013|162,0:236,724,742,789,910|163,0:180|167,0:38,238|169,0:84,257|170,0:99|173,0:702,730,834,876,946|174,0:341,1364,1686|175,0:483,583,597|176,0:327,401,569|178,0:351|179,0:242,258|182,0:195"/><wd nm="ボックスを共有する" rd="73,128:1509"/><wd nm="ボックスインターフェイス" rd="173,0:251"/><wd nm="ボックスビュー" rd="102,0:85"/><wd nm="ボックスフォルダ" rd="3,0:637|70,1:2,27"/><wd nm="ボックスフォルダへのアクセスを受け入れる" rd="70,128:502"/><wd nm="ボレーション" rd="100,0:186|162,0:129|173,0:114"/><wd nm="ボレーションアプリケーション" rd="84,0:186"/><wd nm="ボンコピー" rd="67,0:50,70"/><wd nm="ボート" rd="83,0:316,329,339,349,364"/><wd nm="ボード" rd="94,0:62|107,64:496"/><wd nm="ボードによる移動" rd="176,64:2971"/><wd nm="ボードショートカット" rd="94,0:264|107,128:0,12,275,604|176,0:2146"/><wd nm="ポインタ" rd="5,0:792|11,0:424|48,0:338|66,0:1039|85,0:515,536,601|105,0:532|106,0:158|111,0:61|120,0:211|121,0:341,355,370|174,0:943|181,0:203"/></pk>
